dta_observability/__init__.py
dta_observability/core/__init__.py
dta_observability/core/config.py
dta_observability/core/propagator.py
dta_observability/core/span.py
dta_observability/core/telemetry.py
dta_observability/instrumentation/__init__.py
dta_observability/instrumentation/_create_instrumentors.py
dta_observability/instrumentation/auto.py
dta_observability/instrumentation/base.py
dta_observability/instrumentation/detector.py
dta_observability/instrumentation/instrumentors/__init__.py
dta_observability/instrumentation/instrumentors/celery.py
dta_observability/instrumentation/instrumentors/container.py
dta_observability/instrumentation/instrumentors/faas.py
dta_observability/instrumentation/instrumentors/fastapi.py
dta_observability/instrumentation/instrumentors/flask.py
dta_observability/instrumentation/instrumentors/logging.py
dta_observability/instrumentation/registry.py
dta_observability/instrumentation/utils.py
dta_observability/logging/__init__.py
dta_observability/logging/logger.py
dta_observability/resources/__init__.py
dta_observability/resources/detector.py
dta_observability-0.0.14.dist-info/METADATA
dta_observability-0.0.14.dist-info/WHEEL
dta_observability-0.0.14.dist-info/entry_points.txt
dta_observability-0.0.14.dist-info/RECORD
