Metadata-Version: 2.3
Name: dta-observability
Version: 0.0.14
Summary: Lightweight wrapper around OpenTelemetry core APIs
Author: dta-observability-utils
Author-email: info@totvs.ai
Requires-Python: >=3.10
Classifier: Programming Language :: Python :: 3
Classifier: Programming Language :: Python :: 3.10
Classifier: Programming Language :: Python :: 3.11
Classifier: Programming Language :: Python :: 3.12
Classifier: Programming Language :: Python :: 3.13
Requires-Dist: asyncio (>=3.4.3,<4.0.0)
Requires-Dist: billiard (>=4.2.1,<5.0.0)
Requires-Dist: build (>=1.2.2,<2.0.0)
Requires-Dist: celery (>=5.5.2,<6.0.0)
Requires-Dist: docker (>=7.1.0,<8.0.0)
Requires-Dist: flask (>=2.2.3,<4.0.0)
Requires-Dist: httpx (>=0.28.1,<0.29.0)
Requires-Dist: kubernetes (>=32.0.1,<33.0.0)
Requires-Dist: opentelemetry-api (>=1.33.0,<2.0.0)
Requires-Dist: opentelemetry-exporter-gcp-logging (>=1.9.0a0,<2.0.0)
Requires-Dist: opentelemetry-exporter-gcp-monitoring (>=1.9.0a0,<2.0.0)
Requires-Dist: opentelemetry-exporter-gcp-trace (>=1.9.0,<2.0.0)
Requires-Dist: opentelemetry-exporter-otlp (>=1.33.0,<2.0.0)
Requires-Dist: opentelemetry-instrumentation (>=0.54b,<0.55)
Requires-Dist: opentelemetry-instrumentation-asyncio (>=0.54b,<0.55)
Requires-Dist: opentelemetry-instrumentation-boto (>=0.54b,<0.55)
Requires-Dist: opentelemetry-instrumentation-celery (>=0.54b,<0.55)
Requires-Dist: opentelemetry-instrumentation-django (>=0.54b,<0.55)
Requires-Dist: opentelemetry-instrumentation-fastapi (>=0.54b,<0.55)
Requires-Dist: opentelemetry-instrumentation-flask (>=0.54b,<0.55)
Requires-Dist: opentelemetry-instrumentation-httpx (>=0.54b,<0.55)
Requires-Dist: opentelemetry-instrumentation-logging (>=0.54b,<0.55)
Requires-Dist: opentelemetry-instrumentation-psycopg2 (>=0.54b,<0.55)
Requires-Dist: opentelemetry-instrumentation-pymongo (>=0.54b,<0.55)
Requires-Dist: opentelemetry-instrumentation-requests (>=0.54b,<0.55)
Requires-Dist: opentelemetry-instrumentation-sqlalchemy (>=0.54b,<0.55)
Requires-Dist: opentelemetry-instrumentation-system-metrics (>=0.54b,<0.55)
Requires-Dist: opentelemetry-instrumentation-wsgi (>=0.54b,<0.55)
Requires-Dist: opentelemetry-propagator-gcp (>=1.9.0,<2.0.0)
Requires-Dist: opentelemetry-resourcedetector-gcp (>=1.9.0a0,<2.0.0)
Requires-Dist: opentelemetry-sdk (>=1.33.0,<2.0.0)
Requires-Dist: python-json-logger (>=3.3.0,<4.0.0)
Requires-Dist: requests (>=2.31.0,<3.0.0)
Requires-Dist: setuptools (>=80.4.0,<81.0.0)
Requires-Dist: twine (>=6.1.0,<7.0.0)
Requires-Dist: types-psutil (>=7.0.0.20250401,<8.0.0.0)
Requires-Dist: types-requests (>=2.32.0.20250328,<3.0.0.0)
